setup.py
rssmailer/__init__.py
rssmailer/feed.py
rssmailer/mail.py
rssmailer/rss_mailer.py
rssmailer/scrap.py
rssmailer/template.py
rssmailer.egg-info/PKG-INFO
rssmailer.egg-info/SOURCES.txt
rssmailer.egg-info/dependency_links.txt
rssmailer.egg-info/requires.txt
rssmailer.egg-info/top_level.txt