Metadata-Version: 1.0
Name: rssmailer
Version: 0.3
Summary: RSS Digest Emailer
Home-page: https://tools.indeliblestamp.com
Author: Arun S
Author-email: arun@indeliblestamp.com
License: GPL
Platform: UNKNOWN
